{"AttributeDefinitions":[{"AttributeName":"_id","AttributeType":"S"}],"TableName":"supportrequests","KeySchema":[{"AttributeName":"_id","KeyType":"HASH"}],"TableStatus":"ACTIVE","CreationDateTime":"2021-07-12T20:06:19.976Z","ProvisionedThroughput":{"NumberOfDecreasesToday":0,"ReadCapacityUnits":0,"WriteCapacityUnits":0},"TableSizeBytes":103,"ItemCount":1,"TableArn":"arn:aws:dynamodb:eu-west-2:077341872813:table/supportrequests","TableId":"268bd5b2-2d55-4f33-a89b-c14facbca89c","BillingModeSummary":{"BillingMode":"PAY_PER_REQUEST","LastUpdateToPayPerRequestDateTime":"2021-07-12T20:06:19.976Z"}}